rents_weather/__init__.py
rents_weather/__main__.py
rents_weather/server.py
rents_weather_project-0.1.4.dist-info/METADATA
rents_weather_project-0.1.4.dist-info/WHEEL
rents_weather_project-0.1.4.dist-info/entry_points.txt
rents_weather_project-0.1.4.dist-info/top_level.txt
rents_weather_project-0.1.4.dist-info/RECORD
